<?xml version="1.0" encoding="utf-8" ?>
<c2layout>
    <name>f53</name>
    <sid>177919533739146</sid>
    <event-sheet>layoutMediator</event-sheet>
    <size>
        <width>1280</width>
        <height>720</height>
    </size>
    <margins>
        <horizontal>500</horizontal>
        <vertical>500</vertical>
    </margins>
    <unbounded-scrolling>0</unbounded-scrolling>
    <layers>
        <layer name="Layer 0" sid="453658971420535">
            <initially-visible>1</initially-visible>
            <background-color>255,255,255</background-color>
            <transparent>0</transparent>
            <parallax>
                <x>1</x>
                <y>1</y>
            </parallax>
            <zoom-rate>1</zoom-rate>
            <opacity>1</opacity>
            <force-own-texture>0</force-own-texture>
            <global>0</global>
            <use-render-cells>0</use-render-cells>
            <blend-mode>0</blend-mode>
            <effect-fallback>0</effect-fallback>
            <instances>
                <instance type="groundF" uid="3805">
                    <properties>
                        <initial-visibility>Visible</initial-visibility>
                        <hotspot>Top-left</hotspot>
                    </properties>
                    <blend-mode>0</blend-mode>
                    <effect-fallback>0</effect-fallback>
                    <world>
                        <x>0</x>
                        <y>0</y>
                        <z>0</z>
                        <width>1280</width>
                        <height>720</height>
                        <depth>0</depth>
                        <hotspotX>0</hotspotX>
                        <hotspotY>0</hotspotY>
                        <angle>0</angle>
                        <opacity>1</opacity>
                    </world>
                </instance>
                <instance type="wallF" uid="3806">
                    <properties>
                        <initial-visibility>Visible</initial-visibility>
                        <hotspot>Top-left</hotspot>
                    </properties>
                    <behavior-instances>
                        <behavior-instance type="Solid">
                            <properties>
                                <initial-state>Enabled</initial-state>
                            </properties>
                        </behavior-instance>
                    </behavior-instances>
                    <blend-mode>0</blend-mode>
                    <effect-fallback>0</effect-fallback>
                    <world>
                        <x>1280</x>
                        <y>720</y>
                        <z>0</z>
                        <width>1280</width>
                        <height>64</height>
                        <depth>0</depth>
                        <hotspotX>0</hotspotX>
                        <hotspotY>0</hotspotY>
                        <angle>3.141592741</angle>
                        <opacity>1</opacity>
                    </world>
                </instance>
                <instance type="wallF" uid="3807">
                    <properties>
                        <initial-visibility>Visible</initial-visibility>
                        <hotspot>Top-left</hotspot>
                    </properties>
                    <behavior-instances>
                        <behavior-instance type="Solid">
                            <properties>
                                <initial-state>Enabled</initial-state>
                            </properties>
                        </behavior-instance>
                    </behavior-instances>
                    <blend-mode>0</blend-mode>
                    <effect-fallback>0</effect-fallback>
                    <world>
                        <x>0</x>
                        <y>0</y>
                        <z>0</z>
                        <width>1280</width>
                        <height>64</height>
                        <depth>0</depth>
                        <hotspotX>0</hotspotX>
                        <hotspotY>0</hotspotY>
                        <angle>0</angle>
                        <opacity>1</opacity>
                    </world>
                </instance>
                <instance type="wallF" uid="3808">
                    <properties>
                        <initial-visibility>Visible</initial-visibility>
                        <hotspot>Top-left</hotspot>
                    </properties>
                    <behavior-instances>
                        <behavior-instance type="Solid">
                            <properties>
                                <initial-state>Enabled</initial-state>
                            </properties>
                        </behavior-instance>
                    </behavior-instances>
                    <blend-mode>0</blend-mode>
                    <effect-fallback>0</effect-fallback>
                    <world>
                        <x>1280</x>
                        <y>32</y>
                        <z>0</z>
                        <width>656</width>
                        <height>64</height>
                        <depth>0</depth>
                        <hotspotX>0</hotspotX>
                        <hotspotY>0</hotspotY>
                        <angle>1.570796371</angle>
                        <opacity>1</opacity>
                    </world>
                </instance>
                <instance type="wallF" uid="3809">
                    <properties>
                        <initial-visibility>Visible</initial-visibility>
                        <hotspot>Top-left</hotspot>
                    </properties>
                    <behavior-instances>
                        <behavior-instance type="Solid">
                            <properties>
                                <initial-state>Enabled</initial-state>
                            </properties>
                        </behavior-instance>
                    </behavior-instances>
                    <blend-mode>0</blend-mode>
                    <effect-fallback>0</effect-fallback>
                    <world>
                        <x>0</x>
                        <y>688</y>
                        <z>0</z>
                        <width>656</width>
                        <height>64</height>
                        <depth>0</depth>
                        <hotspotX>0</hotspotX>
                        <hotspotY>0</hotspotY>
                        <angle>-1.570796371</angle>
                        <opacity>1</opacity>
                    </world>
                </instance>
                <instance type="roomSkirting5" uid="3810">
                    <properties>
                        <left-margin>96</left-margin>
                        <right-margin>96</right-margin>
                        <top-margin>96</top-margin>
                        <bottom-margin>96</bottom-margin>
                        <edges>Tile</edges>
                        <fill>Tile</fill>
                        <initial-visibility>Visible</initial-visibility>
                        <hotspot>Top-left</hotspot>
                        <seams>Overlap</seams>
                    </properties>
                    <blend-mode>0</blend-mode>
                    <effect-fallback>0</effect-fallback>
                    <world>
                        <x>0</x>
                        <y>0</y>
                        <z>0</z>
                        <width>1280</width>
                        <height>720</height>
                        <depth>0</depth>
                        <hotspotX>0</hotspotX>
                        <hotspotY>0</hotspotY>
                        <opacity>1</opacity>
                    </world>
                </instance>
            </instances>
            <effects />
        </layer>
        <layer name="Layer 1" sid="995424872238737">
            <initially-visible>1</initially-visible>
            <background-color>255,255,255</background-color>
            <transparent>1</transparent>
            <parallax>
                <x>1</x>
                <y>1</y>
            </parallax>
            <zoom-rate>1</zoom-rate>
            <opacity>1</opacity>
            <force-own-texture>0</force-own-texture>
            <global>0</global>
            <use-render-cells>0</use-render-cells>
            <blend-mode>0</blend-mode>
            <effect-fallback>0</effect-fallback>
            <instances>
                <instance type="doorN" uid="4992">
                    <properties>
                        <initial-visibility>Visible</initial-visibility>
                        <initial-animation>Default</initial-animation>
                        <initial-frame>0</initial-frame>
                        <collisions>Enabled</collisions>
                    </properties>
                    <blend-mode>0</blend-mode>
                    <effect-fallback>0</effect-fallback>
                    <world>
                        <x>64</x>
                        <y>224</y>
                        <z>0</z>
                        <width>64</width>
                        <height>64</height>
                        <depth>0</depth>
                        <hotspotX>0.5</hotspotX>
                        <hotspotY>-0.0625</hotspotY>
                        <angle>0</angle>
                        <opacity>1</opacity>
                    </world>
                </instance>
                <instance type="doorS" uid="4993">
                    <properties>
                        <initial-visibility>Visible</initial-visibility>
                        <initial-animation>Default</initial-animation>
                        <initial-frame>0</initial-frame>
                        <collisions>Enabled</collisions>
                    </properties>
                    <blend-mode>0</blend-mode>
                    <effect-fallback>0</effect-fallback>
                    <world>
                        <x>64</x>
                        <y>512</y>
                        <z>0</z>
                        <width>64</width>
                        <height>64</height>
                        <depth>0</depth>
                        <hotspotX>0.5</hotspotX>
                        <hotspotY>1.0625</hotspotY>
                        <angle>0</angle>
                        <opacity>1</opacity>
                    </world>
                </instance>
                <instance type="doorW" uid="4994">
                    <properties>
                        <initial-visibility>Visible</initial-visibility>
                        <initial-animation>Default</initial-animation>
                        <initial-frame>0</initial-frame>
                        <collisions>Enabled</collisions>
                    </properties>
                    <blend-mode>0</blend-mode>
                    <effect-fallback>0</effect-fallback>
                    <world>
                        <x>32</x>
                        <y>384</y>
                        <z>0</z>
                        <width>64</width>
                        <height>64</height>
                        <depth>0</depth>
                        <hotspotX>-0.0625</hotspotX>
                        <hotspotY>0.5</hotspotY>
                        <angle>0</angle>
                        <opacity>1</opacity>
                    </world>
                </instance>
                <instance type="controlledSpikeType1" uid="5195">
                    <properties>
                        <initial-visibility>Visible</initial-visibility>
                        <initial-animation>Default</initial-animation>
                        <initial-frame>0</initial-frame>
                        <collisions>Enabled</collisions>
                    </properties>
                    <instance-variables>
                        <enemyAttack>1</enemyAttack>
                        <direction>0</direction>
                        <isSafeToTouch>false</isSafeToTouch>
                    </instance-variables>
                    <behavior-instances>
                        <behavior-instance type="BoundToLayout">
                            <properties>
                                <bound-by>Edge</bound-by>
                            </properties>
                        </behavior-instance>
                        <behavior-instance type="8Direction">
                            <properties>
                                <max-speed>400</max-speed>
                                <acceleration>9999</acceleration>
                                <deceleration>9999</deceleration>
                                <directions>4 directions</directions>
                                <set-angle>No</set-angle>
                                <default-controls>No</default-controls>
                                <initial-state>Enabled</initial-state>
                            </properties>
                        </behavior-instance>
                    </behavior-instances>
                    <blend-mode>0</blend-mode>
                    <effect-fallback>0</effect-fallback>
                    <world>
                        <x>512</x>
                        <y>128</y>
                        <z>0</z>
                        <width>64</width>
                        <height>64</height>
                        <depth>0</depth>
                        <hotspotX>0</hotspotX>
                        <hotspotY>0</hotspotY>
                        <angle>0</angle>
                        <opacity>1</opacity>
                    </world>
                </instance>
                <instance type="controlledSpikeType1" uid="5196">
                    <properties>
                        <initial-visibility>Visible</initial-visibility>
                        <initial-animation>Default</initial-animation>
                        <initial-frame>0</initial-frame>
                        <collisions>Enabled</collisions>
                    </properties>
                    <instance-variables>
                        <enemyAttack>1</enemyAttack>
                        <direction>0</direction>
                        <isSafeToTouch>false</isSafeToTouch>
                    </instance-variables>
                    <behavior-instances>
                        <behavior-instance type="BoundToLayout">
                            <properties>
                                <bound-by>Edge</bound-by>
                            </properties>
                        </behavior-instance>
                        <behavior-instance type="8Direction">
                            <properties>
                                <max-speed>400</max-speed>
                                <acceleration>9999</acceleration>
                                <deceleration>9999</deceleration>
                                <directions>4 directions</directions>
                                <set-angle>No</set-angle>
                                <default-controls>No</default-controls>
                                <initial-state>Enabled</initial-state>
                            </properties>
                        </behavior-instance>
                    </behavior-instances>
                    <blend-mode>0</blend-mode>
                    <effect-fallback>0</effect-fallback>
                    <world>
                        <x>448</x>
                        <y>128</y>
                        <z>0</z>
                        <width>64</width>
                        <height>64</height>
                        <depth>0</depth>
                        <hotspotX>0</hotspotX>
                        <hotspotY>0</hotspotY>
                        <angle>0</angle>
                        <opacity>1</opacity>
                    </world>
                </instance>
                <instance type="controlledSpikeType1" uid="5199">
                    <properties>
                        <initial-visibility>Visible</initial-visibility>
                        <initial-animation>Default</initial-animation>
                        <initial-frame>0</initial-frame>
                        <collisions>Enabled</collisions>
                    </properties>
                    <instance-variables>
                        <enemyAttack>1</enemyAttack>
                        <direction>0</direction>
                        <isSafeToTouch>false</isSafeToTouch>
                    </instance-variables>
                    <behavior-instances>
                        <behavior-instance type="BoundToLayout">
                            <properties>
                                <bound-by>Edge</bound-by>
                            </properties>
                        </behavior-instance>
                        <behavior-instance type="8Direction">
                            <properties>
                                <max-speed>400</max-speed>
                                <acceleration>9999</acceleration>
                                <deceleration>9999</deceleration>
                                <directions>4 directions</directions>
                                <set-angle>No</set-angle>
                                <default-controls>No</default-controls>
                                <initial-state>Enabled</initial-state>
                            </properties>
                        </behavior-instance>
                    </behavior-instances>
                    <blend-mode>0</blend-mode>
                    <effect-fallback>0</effect-fallback>
                    <world>
                        <x>448</x>
                        <y>64</y>
                        <z>0</z>
                        <width>64</width>
                        <height>64</height>
                        <depth>0</depth>
                        <hotspotX>0</hotspotX>
                        <hotspotY>0</hotspotY>
                        <angle>0</angle>
                        <opacity>1</opacity>
                    </world>
                </instance>
                <instance type="controlledSpikeType1" uid="5200">
                    <properties>
                        <initial-visibility>Visible</initial-visibility>
                        <initial-animation>Default</initial-animation>
                        <initial-frame>0</initial-frame>
                        <collisions>Enabled</collisions>
                    </properties>
                    <instance-variables>
                        <enemyAttack>1</enemyAttack>
                        <direction>0</direction>
                        <isSafeToTouch>false</isSafeToTouch>
                    </instance-variables>
                    <behavior-instances>
                        <behavior-instance type="BoundToLayout">
                            <properties>
                                <bound-by>Edge</bound-by>
                            </properties>
                        </behavior-instance>
                        <behavior-instance type="8Direction">
                            <properties>
                                <max-speed>400</max-speed>
                                <acceleration>9999</acceleration>
                                <deceleration>9999</deceleration>
                                <directions>4 directions</directions>
                                <set-angle>No</set-angle>
                                <default-controls>No</default-controls>
                                <initial-state>Enabled</initial-state>
                            </properties>
                        </behavior-instance>
                    </behavior-instances>
                    <blend-mode>0</blend-mode>
                    <effect-fallback>0</effect-fallback>
                    <world>
                        <x>512</x>
                        <y>64</y>
                        <z>0</z>
                        <width>64</width>
                        <height>64</height>
                        <depth>0</depth>
                        <hotspotX>0</hotspotX>
                        <hotspotY>0</hotspotY>
                        <angle>0</angle>
                        <opacity>1</opacity>
                    </world>
                </instance>
                <instance type="controlledSpikeType1" uid="5201">
                    <properties>
                        <initial-visibility>Visible</initial-visibility>
                        <initial-animation>Default</initial-animation>
                        <initial-frame>0</initial-frame>
                        <collisions>Enabled</collisions>
                    </properties>
                    <instance-variables>
                        <enemyAttack>1</enemyAttack>
                        <direction>0</direction>
                        <isSafeToTouch>false</isSafeToTouch>
                    </instance-variables>
                    <behavior-instances>
                        <behavior-instance type="BoundToLayout">
                            <properties>
                                <bound-by>Edge</bound-by>
                            </properties>
                        </behavior-instance>
                        <behavior-instance type="8Direction">
                            <properties>
                                <max-speed>400</max-speed>
                                <acceleration>9999</acceleration>
                                <deceleration>9999</deceleration>
                                <directions>4 directions</directions>
                                <set-angle>No</set-angle>
                                <default-controls>No</default-controls>
                                <initial-state>Enabled</initial-state>
                            </properties>
                        </behavior-instance>
                    </behavior-instances>
                    <blend-mode>0</blend-mode>
                    <effect-fallback>0</effect-fallback>
                    <world>
                        <x>576</x>
                        <y>64</y>
                        <z>0</z>
                        <width>64</width>
                        <height>64</height>
                        <depth>0</depth>
                        <hotspotX>0</hotspotX>
                        <hotspotY>0</hotspotY>
                        <angle>0</angle>
                        <opacity>1</opacity>
                    </world>
                </instance>
                <instance type="controlledSpikeType1" uid="5202">
                    <properties>
                        <initial-visibility>Visible</initial-visibility>
                        <initial-animation>Default</initial-animation>
                        <initial-frame>0</initial-frame>
                        <collisions>Enabled</collisions>
                    </properties>
                    <instance-variables>
                        <enemyAttack>1</enemyAttack>
                        <direction>0</direction>
                        <isSafeToTouch>false</isSafeToTouch>
                    </instance-variables>
                    <behavior-instances>
                        <behavior-instance type="BoundToLayout">
                            <properties>
                                <bound-by>Edge</bound-by>
                            </properties>
                        </behavior-instance>
                        <behavior-instance type="8Direction">
                            <properties>
                                <max-speed>400</max-speed>
                                <acceleration>9999</acceleration>
                                <deceleration>9999</deceleration>
                                <directions>4 directions</directions>
                                <set-angle>No</set-angle>
                                <default-controls>No</default-controls>
                                <initial-state>Enabled</initial-state>
                            </properties>
                        </behavior-instance>
                    </behavior-instances>
                    <blend-mode>0</blend-mode>
                    <effect-fallback>0</effect-fallback>
                    <world>
                        <x>640</x>
                        <y>64</y>
                        <z>0</z>
                        <width>64</width>
                        <height>64</height>
                        <depth>0</depth>
                        <hotspotX>0</hotspotX>
                        <hotspotY>0</hotspotY>
                        <angle>0</angle>
                        <opacity>1</opacity>
                    </world>
                </instance>
                <instance type="controlledSpikeType1" uid="5205">
                    <properties>
                        <initial-visibility>Visible</initial-visibility>
                        <initial-animation>Default</initial-animation>
                        <initial-frame>0</initial-frame>
                        <collisions>Enabled</collisions>
                    </properties>
                    <instance-variables>
                        <enemyAttack>1</enemyAttack>
                        <direction>0</direction>
                        <isSafeToTouch>false</isSafeToTouch>
                    </instance-variables>
                    <behavior-instances>
                        <behavior-instance type="BoundToLayout">
                            <properties>
                                <bound-by>Edge</bound-by>
                            </properties>
                        </behavior-instance>
                        <behavior-instance type="8Direction">
                            <properties>
                                <max-speed>400</max-speed>
                                <acceleration>9999</acceleration>
                                <deceleration>9999</deceleration>
                                <directions>4 directions</directions>
                                <set-angle>No</set-angle>
                                <default-controls>No</default-controls>
                                <initial-state>Enabled</initial-state>
                            </properties>
                        </behavior-instance>
                    </behavior-instances>
                    <blend-mode>0</blend-mode>
                    <effect-fallback>0</effect-fallback>
                    <world>
                        <x>704</x>
                        <y>64</y>
                        <z>0</z>
                        <width>64</width>
                        <height>64</height>
                        <depth>0</depth>
                        <hotspotX>0</hotspotX>
                        <hotspotY>0</hotspotY>
                        <angle>0</angle>
                        <opacity>1</opacity>
                    </world>
                </instance>
                <instance type="controlledSpikeType1" uid="5206">
                    <properties>
                        <initial-visibility>Visible</initial-visibility>
                        <initial-animation>Default</initial-animation>
                        <initial-frame>0</initial-frame>
                        <collisions>Enabled</collisions>
                    </properties>
                    <instance-variables>
                        <enemyAttack>1</enemyAttack>
                        <direction>0</direction>
                        <isSafeToTouch>false</isSafeToTouch>
                    </instance-variables>
                    <behavior-instances>
                        <behavior-instance type="BoundToLayout">
                            <properties>
                                <bound-by>Edge</bound-by>
                            </properties>
                        </behavior-instance>
                        <behavior-instance type="8Direction">
                            <properties>
                                <max-speed>400</max-speed>
                                <acceleration>9999</acceleration>
                                <deceleration>9999</deceleration>
                                <directions>4 directions</directions>
                                <set-angle>No</set-angle>
                                <default-controls>No</default-controls>
                                <initial-state>Enabled</initial-state>
                            </properties>
                        </behavior-instance>
                    </behavior-instances>
                    <blend-mode>0</blend-mode>
                    <effect-fallback>0</effect-fallback>
                    <world>
                        <x>768</x>
                        <y>64</y>
                        <z>0</z>
                        <width>64</width>
                        <height>64</height>
                        <depth>0</depth>
                        <hotspotX>0</hotspotX>
                        <hotspotY>0</hotspotY>
                        <angle>0</angle>
                        <opacity>1</opacity>
                    </world>
                </instance>
                <instance type="controlledSpikeType1" uid="5207">
                    <properties>
                        <initial-visibility>Visible</initial-visibility>
                        <initial-animation>Default</initial-animation>
                        <initial-frame>0</initial-frame>
                        <collisions>Enabled</collisions>
                    </properties>
                    <instance-variables>
                        <enemyAttack>1</enemyAttack>
                        <direction>0</direction>
                        <isSafeToTouch>false</isSafeToTouch>
                    </instance-variables>
                    <behavior-instances>
                        <behavior-instance type="BoundToLayout">
                            <properties>
                                <bound-by>Edge</bound-by>
                            </properties>
                        </behavior-instance>
                        <behavior-instance type="8Direction">
                            <properties>
                                <max-speed>400</max-speed>
                                <acceleration>9999</acceleration>
                                <deceleration>9999</deceleration>
                                <directions>4 directions</directions>
                                <set-angle>No</set-angle>
                                <default-controls>No</default-controls>
                                <initial-state>Enabled</initial-state>
                            </properties>
                        </behavior-instance>
                    </behavior-instances>
                    <blend-mode>0</blend-mode>
                    <effect-fallback>0</effect-fallback>
                    <world>
                        <x>768</x>
                        <y>128</y>
                        <z>0</z>
                        <width>64</width>
                        <height>64</height>
                        <depth>0</depth>
                        <hotspotX>0</hotspotX>
                        <hotspotY>0</hotspotY>
                        <angle>0</angle>
                        <opacity>1</opacity>
                    </world>
                </instance>
                <instance type="controlledSpikeType1" uid="5208">
                    <properties>
                        <initial-visibility>Visible</initial-visibility>
                        <initial-animation>Default</initial-animation>
                        <initial-frame>0</initial-frame>
                        <collisions>Enabled</collisions>
                    </properties>
                    <instance-variables>
                        <enemyAttack>1</enemyAttack>
                        <direction>0</direction>
                        <isSafeToTouch>false</isSafeToTouch>
                    </instance-variables>
                    <behavior-instances>
                        <behavior-instance type="BoundToLayout">
                            <properties>
                                <bound-by>Edge</bound-by>
                            </properties>
                        </behavior-instance>
                        <behavior-instance type="8Direction">
                            <properties>
                                <max-speed>400</max-speed>
                                <acceleration>9999</acceleration>
                                <deceleration>9999</deceleration>
                                <directions>4 directions</directions>
                                <set-angle>No</set-angle>
                                <default-controls>No</default-controls>
                                <initial-state>Enabled</initial-state>
                            </properties>
                        </behavior-instance>
                    </behavior-instances>
                    <blend-mode>0</blend-mode>
                    <effect-fallback>0</effect-fallback>
                    <world>
                        <x>704</x>
                        <y>128</y>
                        <z>0</z>
                        <width>64</width>
                        <height>64</height>
                        <depth>0</depth>
                        <hotspotX>0</hotspotX>
                        <hotspotY>0</hotspotY>
                        <angle>0</angle>
                        <opacity>1</opacity>
                    </world>
                </instance>
                <instance type="controlledSpikeType1" uid="5209">
                    <properties>
                        <initial-visibility>Visible</initial-visibility>
                        <initial-animation>Default</initial-animation>
                        <initial-frame>0</initial-frame>
                        <collisions>Enabled</collisions>
                    </properties>
                    <instance-variables>
                        <enemyAttack>1</enemyAttack>
                        <direction>0</direction>
                        <isSafeToTouch>false</isSafeToTouch>
                    </instance-variables>
                    <behavior-instances>
                        <behavior-instance type="BoundToLayout">
                            <properties>
                                <bound-by>Edge</bound-by>
                            </properties>
                        </behavior-instance>
                        <behavior-instance type="8Direction">
                            <properties>
                                <max-speed>400</max-speed>
                                <acceleration>9999</acceleration>
                                <deceleration>9999</deceleration>
                                <directions>4 directions</directions>
                                <set-angle>No</set-angle>
                                <default-controls>No</default-controls>
                                <initial-state>Enabled</initial-state>
                            </properties>
                        </behavior-instance>
                    </behavior-instances>
                    <blend-mode>0</blend-mode>
                    <effect-fallback>0</effect-fallback>
                    <world>
                        <x>640</x>
                        <y>128</y>
                        <z>0</z>
                        <width>64</width>
                        <height>64</height>
                        <depth>0</depth>
                        <hotspotX>0</hotspotX>
                        <hotspotY>0</hotspotY>
                        <angle>0</angle>
                        <opacity>1</opacity>
                    </world>
                </instance>
                <instance type="controlledSpikeType1" uid="5210">
                    <properties>
                        <initial-visibility>Visible</initial-visibility>
                        <initial-animation>Default</initial-animation>
                        <initial-frame>0</initial-frame>
                        <collisions>Enabled</collisions>
                    </properties>
                    <instance-variables>
                        <enemyAttack>1</enemyAttack>
                        <direction>0</direction>
                        <isSafeToTouch>false</isSafeToTouch>
                    </instance-variables>
                    <behavior-instances>
                        <behavior-instance type="BoundToLayout">
                            <properties>
                                <bound-by>Edge</bound-by>
                            </properties>
                        </behavior-instance>
                        <behavior-instance type="8Direction">
                            <properties>
                                <max-speed>400</max-speed>
                                <acceleration>9999</acceleration>
                                <deceleration>9999</deceleration>
                                <directions>4 directions</directions>
                                <set-angle>No</set-angle>
                                <default-controls>No</default-controls>
                                <initial-state>Enabled</initial-state>
                            </properties>
                        </behavior-instance>
                    </behavior-instances>
                    <blend-mode>0</blend-mode>
                    <effect-fallback>0</effect-fallback>
                    <world>
                        <x>576</x>
                        <y>128</y>
                        <z>0</z>
                        <width>64</width>
                        <height>64</height>
                        <depth>0</depth>
                        <hotspotX>0</hotspotX>
                        <hotspotY>0</hotspotY>
                        <angle>0</angle>
                        <opacity>1</opacity>
                    </world>
                </instance>
                <instance type="enemy15" uid="5143">
                    <properties>
                        <initial-visibility>Visible</initial-visibility>
                        <initial-animation>Default</initial-animation>
                        <initial-frame>0</initial-frame>
                        <collisions>Enabled</collisions>
                    </properties>
                    <instance-variables>
                        <canBeHarmed>true</canBeHarmed>
                        <enemyHP>4</enemyHP>
                        <enemyAttack>2</enemyAttack>
                        <isShooting>false</isShooting>
                        <isRandomlyMoving>false</isRandomlyMoving>
                        <canBeStunned>false</canBeStunned>
                        <randomPrize>0</randomPrize>
                        <visibleTime>1</visibleTime>
                        <shootTime>1</shootTime>
                        <randomNumber>0</randomNumber>
                    </instance-variables>
                    <behavior-instances>
                        <behavior-instance type="Flash2" />
                        <behavior-instance type="DestroyOutsideLayout" />
                        <behavior-instance type="8Direction2">
                            <properties>
                                <max-speed>400</max-speed>
                                <acceleration>600</acceleration>
                                <deceleration>500</deceleration>
                                <directions>4 directions</directions>
                                <set-angle>No</set-angle>
                                <default-controls>No</default-controls>
                                <initial-state>Enabled</initial-state>
                            </properties>
                        </behavior-instance>
                    </behavior-instances>
                    <blend-mode>0</blend-mode>
                    <effect-fallback>0</effect-fallback>
                    <world>
                        <x>608</x>
                        <y>320</y>
                        <z>0</z>
                        <width>64</width>
                        <height>64</height>
                        <depth>0</depth>
                        <hotspotX>0.5</hotspotX>
                        <hotspotY>0.5</hotspotY>
                        <angle>0</angle>
                        <opacity>1</opacity>
                    </world>
                </instance>
                <instance type="enemy17" uid="5579">
                    <properties>
                        <initial-visibility>Visible</initial-visibility>
                        <initial-animation>Default</initial-animation>
                        <initial-frame>0</initial-frame>
                        <collisions>Enabled</collisions>
                    </properties>
                    <instance-variables>
                        <canBeHarmed>true</canBeHarmed>
                        <enemyHP>4</enemyHP>
                        <enemyAttack>1</enemyAttack>
                        <isShooting>false</isShooting>
                        <isRandomlyMoving>false</isRandomlyMoving>
                        <canBeStunned>false</canBeStunned>
                        <randomPrize>0</randomPrize>
                        <has90degRotation>false</has90degRotation>
                        <randomNumber>0</randomNumber>
                        <isStunned>false</isStunned>
                        <timeGap>0.3</timeGap>
                    </instance-variables>
                    <behavior-instances>
                        <behavior-instance type="Flash2" />
                        <behavior-instance type="DestroyOutsideLayout" />
                        <behavior-instance type="8Direction2">
                            <properties>
                                <max-speed>1000</max-speed>
                                <acceleration>600</acceleration>
                                <deceleration>500</deceleration>
                                <directions>8 directions</directions>
                                <set-angle>90-degree intervals</set-angle>
                                <default-controls>No</default-controls>
                                <initial-state>Enabled</initial-state>
                            </properties>
                        </behavior-instance>
                        <behavior-instance type="BoundToLayout">
                            <properties>
                                <bound-by>Edge</bound-by>
                            </properties>
                        </behavior-instance>
                        <behavior-instance type="8Direction">
                            <properties>
                                <max-speed>200</max-speed>
                                <acceleration>9999</acceleration>
                                <deceleration>9999</deceleration>
                                <directions>4 directions</directions>
                                <set-angle>No</set-angle>
                                <default-controls>No</default-controls>
                                <initial-state>Enabled</initial-state>
                            </properties>
                        </behavior-instance>
                        <behavior-instance type="Solid">
                            <properties>
                                <initial-state>Enabled</initial-state>
                            </properties>
                        </behavior-instance>
                    </behavior-instances>
                    <blend-mode>0</blend-mode>
                    <effect-fallback>0</effect-fallback>
                    <world>
                        <x>1056</x>
                        <y>384</y>
                        <z>0</z>
                        <width>64</width>
                        <height>64</height>
                        <depth>0</depth>
                        <hotspotX>0.5</hotspotX>
                        <hotspotY>0.5</hotspotY>
                        <angle>0</angle>
                        <opacity>1</opacity>
                    </world>
                </instance>
                <instance type="controlledSpikeType0" uid="5784">
                    <properties>
                        <initial-visibility>Visible</initial-visibility>
                        <initial-animation>Default</initial-animation>
                        <initial-frame>0</initial-frame>
                        <collisions>Enabled</collisions>
                    </properties>
                    <instance-variables>
                        <enemyAttack>1</enemyAttack>
                        <direction>0</direction>
                        <isSafeToTouch>false</isSafeToTouch>
                    </instance-variables>
                    <behavior-instances>
                        <behavior-instance type="BoundToLayout">
                            <properties>
                                <bound-by>Edge</bound-by>
                            </properties>
                        </behavior-instance>
                        <behavior-instance type="8Direction">
                            <properties>
                                <max-speed>200</max-speed>
                                <acceleration>600</acceleration>
                                <deceleration>500</deceleration>
                                <directions>Up &amp; down</directions>
                                <set-angle>No</set-angle>
                                <default-controls>No</default-controls>
                                <initial-state>Enabled</initial-state>
                            </properties>
                        </behavior-instance>
                    </behavior-instances>
                    <blend-mode>0</blend-mode>
                    <effect-fallback>0</effect-fallback>
                    <world>
                        <x>64</x>
                        <y>64</y>
                        <z>0</z>
                        <width>64</width>
                        <height>64</height>
                        <depth>0</depth>
                        <hotspotX>0</hotspotX>
                        <hotspotY>0</hotspotY>
                        <angle>0</angle>
                        <opacity>1</opacity>
                    </world>
                </instance>
                <instance type="controlledSpikeType0" uid="5785">
                    <properties>
                        <initial-visibility>Visible</initial-visibility>
                        <initial-animation>Default</initial-animation>
                        <initial-frame>0</initial-frame>
                        <collisions>Enabled</collisions>
                    </properties>
                    <instance-variables>
                        <enemyAttack>1</enemyAttack>
                        <direction>0</direction>
                        <isSafeToTouch>false</isSafeToTouch>
                    </instance-variables>
                    <behavior-instances>
                        <behavior-instance type="BoundToLayout">
                            <properties>
                                <bound-by>Edge</bound-by>
                            </properties>
                        </behavior-instance>
                        <behavior-instance type="8Direction">
                            <properties>
                                <max-speed>200</max-speed>
                                <acceleration>600</acceleration>
                                <deceleration>500</deceleration>
                                <directions>Up &amp; down</directions>
                                <set-angle>No</set-angle>
                                <default-controls>No</default-controls>
                                <initial-state>Enabled</initial-state>
                            </properties>
                        </behavior-instance>
                    </behavior-instances>
                    <blend-mode>0</blend-mode>
                    <effect-fallback>0</effect-fallback>
                    <world>
                        <x>128</x>
                        <y>64</y>
                        <z>0</z>
                        <width>64</width>
                        <height>64</height>
                        <depth>0</depth>
                        <hotspotX>0</hotspotX>
                        <hotspotY>0</hotspotY>
                        <angle>0</angle>
                        <opacity>1</opacity>
                    </world>
                </instance>
                <instance type="controlledSpikeType0" uid="5786">
                    <properties>
                        <initial-visibility>Visible</initial-visibility>
                        <initial-animation>Default</initial-animation>
                        <initial-frame>0</initial-frame>
                        <collisions>Enabled</collisions>
                    </properties>
                    <instance-variables>
                        <enemyAttack>1</enemyAttack>
                        <direction>0</direction>
                        <isSafeToTouch>false</isSafeToTouch>
                    </instance-variables>
                    <behavior-instances>
                        <behavior-instance type="BoundToLayout">
                            <properties>
                                <bound-by>Edge</bound-by>
                            </properties>
                        </behavior-instance>
                        <behavior-instance type="8Direction">
                            <properties>
                                <max-speed>200</max-speed>
                                <acceleration>600</acceleration>
                                <deceleration>500</deceleration>
                                <directions>Up &amp; down</directions>
                                <set-angle>No</set-angle>
                                <default-controls>No</default-controls>
                                <initial-state>Enabled</initial-state>
                            </properties>
                        </behavior-instance>
                    </behavior-instances>
                    <blend-mode>0</blend-mode>
                    <effect-fallback>0</effect-fallback>
                    <world>
                        <x>64</x>
                        <y>128</y>
                        <z>0</z>
                        <width>64</width>
                        <height>64</height>
                        <depth>0</depth>
                        <hotspotX>0</hotspotX>
                        <hotspotY>0</hotspotY>
                        <angle>0</angle>
                        <opacity>1</opacity>
                    </world>
                </instance>
                <instance type="controlledSpikeType0" uid="5788">
                    <properties>
                        <initial-visibility>Visible</initial-visibility>
                        <initial-animation>Default</initial-animation>
                        <initial-frame>0</initial-frame>
                        <collisions>Enabled</collisions>
                    </properties>
                    <instance-variables>
                        <enemyAttack>1</enemyAttack>
                        <direction>0</direction>
                        <isSafeToTouch>false</isSafeToTouch>
                    </instance-variables>
                    <behavior-instances>
                        <behavior-instance type="BoundToLayout">
                            <properties>
                                <bound-by>Edge</bound-by>
                            </properties>
                        </behavior-instance>
                        <behavior-instance type="8Direction">
                            <properties>
                                <max-speed>200</max-speed>
                                <acceleration>600</acceleration>
                                <deceleration>500</deceleration>
                                <directions>Up &amp; down</directions>
                                <set-angle>No</set-angle>
                                <default-controls>No</default-controls>
                                <initial-state>Enabled</initial-state>
                            </properties>
                        </behavior-instance>
                    </behavior-instances>
                    <blend-mode>0</blend-mode>
                    <effect-fallback>0</effect-fallback>
                    <world>
                        <x>1088</x>
                        <y>64</y>
                        <z>0</z>
                        <width>64</width>
                        <height>64</height>
                        <depth>0</depth>
                        <hotspotX>0</hotspotX>
                        <hotspotY>0</hotspotY>
                        <angle>0</angle>
                        <opacity>1</opacity>
                    </world>
                </instance>
                <instance type="controlledSpikeType0" uid="5789">
                    <properties>
                        <initial-visibility>Visible</initial-visibility>
                        <initial-animation>Default</initial-animation>
                        <initial-frame>0</initial-frame>
                        <collisions>Enabled</collisions>
                    </properties>
                    <instance-variables>
                        <enemyAttack>1</enemyAttack>
                        <direction>0</direction>
                        <isSafeToTouch>false</isSafeToTouch>
                    </instance-variables>
                    <behavior-instances>
                        <behavior-instance type="BoundToLayout">
                            <properties>
                                <bound-by>Edge</bound-by>
                            </properties>
                        </behavior-instance>
                        <behavior-instance type="8Direction">
                            <properties>
                                <max-speed>200</max-speed>
                                <acceleration>600</acceleration>
                                <deceleration>500</deceleration>
                                <directions>Up &amp; down</directions>
                                <set-angle>No</set-angle>
                                <default-controls>No</default-controls>
                                <initial-state>Enabled</initial-state>
                            </properties>
                        </behavior-instance>
                    </behavior-instances>
                    <blend-mode>0</blend-mode>
                    <effect-fallback>0</effect-fallback>
                    <world>
                        <x>1152</x>
                        <y>64</y>
                        <z>0</z>
                        <width>64</width>
                        <height>64</height>
                        <depth>0</depth>
                        <hotspotX>0</hotspotX>
                        <hotspotY>0</hotspotY>
                        <angle>0</angle>
                        <opacity>1</opacity>
                    </world>
                </instance>
                <instance type="controlledSpikeType0" uid="5791">
                    <properties>
                        <initial-visibility>Visible</initial-visibility>
                        <initial-animation>Default</initial-animation>
                        <initial-frame>0</initial-frame>
                        <collisions>Enabled</collisions>
                    </properties>
                    <instance-variables>
                        <enemyAttack>1</enemyAttack>
                        <direction>0</direction>
                        <isSafeToTouch>false</isSafeToTouch>
                    </instance-variables>
                    <behavior-instances>
                        <behavior-instance type="BoundToLayout">
                            <properties>
                                <bound-by>Edge</bound-by>
                            </properties>
                        </behavior-instance>
                        <behavior-instance type="8Direction">
                            <properties>
                                <max-speed>200</max-speed>
                                <acceleration>600</acceleration>
                                <deceleration>500</deceleration>
                                <directions>Up &amp; down</directions>
                                <set-angle>No</set-angle>
                                <default-controls>No</default-controls>
                                <initial-state>Enabled</initial-state>
                            </properties>
                        </behavior-instance>
                    </behavior-instances>
                    <blend-mode>0</blend-mode>
                    <effect-fallback>0</effect-fallback>
                    <world>
                        <x>1152</x>
                        <y>128</y>
                        <z>0</z>
                        <width>64</width>
                        <height>64</height>
                        <depth>0</depth>
                        <hotspotX>0</hotspotX>
                        <hotspotY>0</hotspotY>
                        <angle>0</angle>
                        <opacity>1</opacity>
                    </world>
                </instance>
                <instance type="controlledSpikeType0" uid="5793">
                    <properties>
                        <initial-visibility>Visible</initial-visibility>
                        <initial-animation>Default</initial-animation>
                        <initial-frame>0</initial-frame>
                        <collisions>Enabled</collisions>
                    </properties>
                    <instance-variables>
                        <enemyAttack>1</enemyAttack>
                        <direction>0</direction>
                        <isSafeToTouch>false</isSafeToTouch>
                    </instance-variables>
                    <behavior-instances>
                        <behavior-instance type="BoundToLayout">
                            <properties>
                                <bound-by>Edge</bound-by>
                            </properties>
                        </behavior-instance>
                        <behavior-instance type="8Direction">
                            <properties>
                                <max-speed>200</max-speed>
                                <acceleration>600</acceleration>
                                <deceleration>500</deceleration>
                                <directions>Up &amp; down</directions>
                                <set-angle>No</set-angle>
                                <default-controls>No</default-controls>
                                <initial-state>Enabled</initial-state>
                            </properties>
                        </behavior-instance>
                    </behavior-instances>
                    <blend-mode>0</blend-mode>
                    <effect-fallback>0</effect-fallback>
                    <world>
                        <x>1152</x>
                        <y>512</y>
                        <z>0</z>
                        <width>64</width>
                        <height>64</height>
                        <depth>0</depth>
                        <hotspotX>0</hotspotX>
                        <hotspotY>0</hotspotY>
                        <angle>0</angle>
                        <opacity>1</opacity>
                    </world>
                </instance>
                <instance type="controlledSpikeType0" uid="5794">
                    <properties>
                        <initial-visibility>Visible</initial-visibility>
                        <initial-animation>Default</initial-animation>
                        <initial-frame>0</initial-frame>
                        <collisions>Enabled</collisions>
                    </properties>
                    <instance-variables>
                        <enemyAttack>1</enemyAttack>
                        <direction>0</direction>
                        <isSafeToTouch>false</isSafeToTouch>
                    </instance-variables>
                    <behavior-instances>
                        <behavior-instance type="BoundToLayout">
                            <properties>
                                <bound-by>Edge</bound-by>
                            </properties>
                        </behavior-instance>
                        <behavior-instance type="8Direction">
                            <properties>
                                <max-speed>200</max-speed>
                                <acceleration>600</acceleration>
                                <deceleration>500</deceleration>
                                <directions>Up &amp; down</directions>
                                <set-angle>No</set-angle>
                                <default-controls>No</default-controls>
                                <initial-state>Enabled</initial-state>
                            </properties>
                        </behavior-instance>
                    </behavior-instances>
                    <blend-mode>0</blend-mode>
                    <effect-fallback>0</effect-fallback>
                    <world>
                        <x>1088</x>
                        <y>576</y>
                        <z>0</z>
                        <width>64</width>
                        <height>64</height>
                        <depth>0</depth>
                        <hotspotX>0</hotspotX>
                        <hotspotY>0</hotspotY>
                        <angle>0</angle>
                        <opacity>1</opacity>
                    </world>
                </instance>
                <instance type="controlledSpikeType0" uid="5795">
                    <properties>
                        <initial-visibility>Visible</initial-visibility>
                        <initial-animation>Default</initial-animation>
                        <initial-frame>0</initial-frame>
                        <collisions>Enabled</collisions>
                    </properties>
                    <instance-variables>
                        <enemyAttack>1</enemyAttack>
                        <direction>0</direction>
                        <isSafeToTouch>false</isSafeToTouch>
                    </instance-variables>
                    <behavior-instances>
                        <behavior-instance type="BoundToLayout">
                            <properties>
                                <bound-by>Edge</bound-by>
                            </properties>
                        </behavior-instance>
                        <behavior-instance type="8Direction">
                            <properties>
                                <max-speed>200</max-speed>
                                <acceleration>600</acceleration>
                                <deceleration>500</deceleration>
                                <directions>Up &amp; down</directions>
                                <set-angle>No</set-angle>
                                <default-controls>No</default-controls>
                                <initial-state>Enabled</initial-state>
                            </properties>
                        </behavior-instance>
                    </behavior-instances>
                    <blend-mode>0</blend-mode>
                    <effect-fallback>0</effect-fallback>
                    <world>
                        <x>1152</x>
                        <y>576</y>
                        <z>0</z>
                        <width>64</width>
                        <height>64</height>
                        <depth>0</depth>
                        <hotspotX>0</hotspotX>
                        <hotspotY>0</hotspotY>
                        <angle>0</angle>
                        <opacity>1</opacity>
                    </world>
                </instance>
                <instance type="controlledSpikeType0" uid="5796">
                    <properties>
                        <initial-visibility>Visible</initial-visibility>
                        <initial-animation>Default</initial-animation>
                        <initial-frame>0</initial-frame>
                        <collisions>Enabled</collisions>
                    </properties>
                    <instance-variables>
                        <enemyAttack>1</enemyAttack>
                        <direction>0</direction>
                        <isSafeToTouch>false</isSafeToTouch>
                    </instance-variables>
                    <behavior-instances>
                        <behavior-instance type="BoundToLayout">
                            <properties>
                                <bound-by>Edge</bound-by>
                            </properties>
                        </behavior-instance>
                        <behavior-instance type="8Direction">
                            <properties>
                                <max-speed>200</max-speed>
                                <acceleration>600</acceleration>
                                <deceleration>500</deceleration>
                                <directions>Up &amp; down</directions>
                                <set-angle>No</set-angle>
                                <default-controls>No</default-controls>
                                <initial-state>Enabled</initial-state>
                            </properties>
                        </behavior-instance>
                    </behavior-instances>
                    <blend-mode>0</blend-mode>
                    <effect-fallback>0</effect-fallback>
                    <world>
                        <x>64</x>
                        <y>512</y>
                        <z>0</z>
                        <width>64</width>
                        <height>64</height>
                        <depth>0</depth>
                        <hotspotX>0</hotspotX>
                        <hotspotY>0</hotspotY>
                        <angle>0</angle>
                        <opacity>1</opacity>
                    </world>
                </instance>
                <instance type="controlledSpikeType0" uid="5798">
                    <properties>
                        <initial-visibility>Visible</initial-visibility>
                        <initial-animation>Default</initial-animation>
                        <initial-frame>0</initial-frame>
                        <collisions>Enabled</collisions>
                    </properties>
                    <instance-variables>
                        <enemyAttack>1</enemyAttack>
                        <direction>0</direction>
                        <isSafeToTouch>false</isSafeToTouch>
                    </instance-variables>
                    <behavior-instances>
                        <behavior-instance type="BoundToLayout">
                            <properties>
                                <bound-by>Edge</bound-by>
                            </properties>
                        </behavior-instance>
                        <behavior-instance type="8Direction">
                            <properties>
                                <max-speed>200</max-speed>
                                <acceleration>600</acceleration>
                                <deceleration>500</deceleration>
                                <directions>Up &amp; down</directions>
                                <set-angle>No</set-angle>
                                <default-controls>No</default-controls>
                                <initial-state>Enabled</initial-state>
                            </properties>
                        </behavior-instance>
                    </behavior-instances>
                    <blend-mode>0</blend-mode>
                    <effect-fallback>0</effect-fallback>
                    <world>
                        <x>64</x>
                        <y>576</y>
                        <z>0</z>
                        <width>64</width>
                        <height>64</height>
                        <depth>0</depth>
                        <hotspotX>0</hotspotX>
                        <hotspotY>0</hotspotY>
                        <angle>0</angle>
                        <opacity>1</opacity>
                    </world>
                </instance>
                <instance type="controlledSpikeType0" uid="5799">
                    <properties>
                        <initial-visibility>Visible</initial-visibility>
                        <initial-animation>Default</initial-animation>
                        <initial-frame>0</initial-frame>
                        <collisions>Enabled</collisions>
                    </properties>
                    <instance-variables>
                        <enemyAttack>1</enemyAttack>
                        <direction>0</direction>
                        <isSafeToTouch>false</isSafeToTouch>
                    </instance-variables>
                    <behavior-instances>
                        <behavior-instance type="BoundToLayout">
                            <properties>
                                <bound-by>Edge</bound-by>
                            </properties>
                        </behavior-instance>
                        <behavior-instance type="8Direction">
                            <properties>
                                <max-speed>200</max-speed>
                                <acceleration>600</acceleration>
                                <deceleration>500</deceleration>
                                <directions>Up &amp; down</directions>
                                <set-angle>No</set-angle>
                                <default-controls>No</default-controls>
                                <initial-state>Enabled</initial-state>
                            </properties>
                        </behavior-instance>
                    </behavior-instances>
                    <blend-mode>0</blend-mode>
                    <effect-fallback>0</effect-fallback>
                    <world>
                        <x>128</x>
                        <y>576</y>
                        <z>0</z>
                        <width>64</width>
                        <height>64</height>
                        <depth>0</depth>
                        <hotspotX>0</hotspotX>
                        <hotspotY>0</hotspotY>
                        <angle>0</angle>
                        <opacity>1</opacity>
                    </world>
                </instance>
            </instances>
            <effects />
        </layer>
        <layer name="Layer 2" sid="563435956618280">
            <initially-visible>1</initially-visible>
            <background-color>255,255,255</background-color>
            <transparent>1</transparent>
            <parallax>
                <x>1</x>
                <y>1</y>
            </parallax>
            <zoom-rate>1</zoom-rate>
            <opacity>1</opacity>
            <force-own-texture>0</force-own-texture>
            <global>0</global>
            <use-render-cells>0</use-render-cells>
            <blend-mode>0</blend-mode>
            <effect-fallback>0</effect-fallback>
            <instances />
            <effects />
        </layer>
    </layers>
    <nonworld-instances />
    <effects />
</c2layout>
